dask_progress_matrix/__init__.py
dask_progress_matrix/__main__.py
dask_progress_matrix/cli.py
dask_progress_matrix/display.py
dask_progress_matrix/progress.py
dask_progress_matrix/status.py
dask_progress_matrix/types.py
dask_progress_matrix/utils.py
dask_progress_matrix-0.0.1.dist-info/WHEEL
dask_progress_matrix-0.0.1.dist-info/entry_points.txt
dask_progress_matrix-0.0.1.dist-info/METADATA
dask_progress_matrix-0.0.1.dist-info/RECORD
