Metadata-Version: 2.3
Name: dask-progress-matrix
Version: 0.0.1
Summary: A 2D progress matrix for visualizing Dask computations by chunk.
Author: Aaron Zuspan
Author-email: Aaron Zuspan <aa.zuspan@gmail.com>
Requires-Dist: dask
Requires-Dist: numpy
Requires-Dist: rich
Requires-Dist: typing-extensions
Requires-Python: >=3.10
